ovos_skill_date_time/LICENSE
ovos_skill_date_time/MANIFEST.in
ovos_skill_date_time/README.md
ovos_skill_date_time/__init__.py
ovos_skill_date_time/requirements.txt
ovos_skill_date_time/settingsmeta.json
ovos_skill_date_time/version.py
ovos_skill_date_time/gui/qt5/date.qml
ovos_skill_date_time/gui/qt5/time.qml
ovos_skill_date_time/locale/ca-es/location.rx
ovos_skill_date_time/locale/ca-es/offset.entity
ovos_skill_date_time/locale/ca-es/skill.json
ovos_skill_date_time/locale/ca-es/timezone.value
ovos_skill_date_time/locale/ca-es/dialog/date.dialog
ovos_skill_date_time/locale/ca-es/dialog/date.future.weekend.dialog
ovos_skill_date_time/locale/ca-es/dialog/date.last.weekend.dialog
ovos_skill_date_time/locale/ca-es/dialog/date.not.found.dialog
ovos_skill_date_time/locale/ca-es/dialog/date.relative.future.dialog
ovos_skill_date_time/locale/ca-es/dialog/date.relative.past.dialog
ovos_skill_date_time/locale/ca-es/dialog/day.current.dialog
ovos_skill_date_time/locale/ca-es/dialog/did.you.mean.timezone.dialog
ovos_skill_date_time/locale/ca-es/dialog/month.current.dialog
ovos_skill_date_time/locale/ca-es/dialog/next.leap.year.dialog
ovos_skill_date_time/locale/ca-es/dialog/time.current.dialog
ovos_skill_date_time/locale/ca-es/dialog/time.future.dialog
ovos_skill_date_time/locale/ca-es/dialog/time.tz.not.found.dialog
ovos_skill_date_time/locale/ca-es/dialog/weekday.current.dialog
ovos_skill_date_time/locale/ca-es/dialog/year.current.dialog
ovos_skill_date_time/locale/ca-es/intents/date.future.weekend.intent
ovos_skill_date_time/locale/ca-es/intents/date.last.weekend.intent
ovos_skill_date_time/locale/ca-es/intents/what.day.is.it.intent
ovos_skill_date_time/locale/ca-es/intents/what.month.is.it.intent
ovos_skill_date_time/locale/ca-es/intents/what.time.is.it.intent
ovos_skill_date_time/locale/ca-es/intents/what.time.will.it.be.intent
ovos_skill_date_time/locale/ca-es/intents/what.weekday.is.it.intent
ovos_skill_date_time/locale/ca-es/intents/what.year.is.it.intent
ovos_skill_date_time/ovos_skill_date_time.egg-info/PKG-INFO
ovos_skill_date_time/ovos_skill_date_time.egg-info/SOURCES.txt
ovos_skill_date_time/ovos_skill_date_time.egg-info/dependency_links.txt
ovos_skill_date_time/ovos_skill_date_time.egg-info/entry_points.txt
ovos_skill_date_time/ovos_skill_date_time.egg-info/requires.txt
ovos_skill_date_time/ovos_skill_date_time.egg-info/top_level.txt
ovos_skill_date_time-1.1.5.dist-info/LICENSE
ovos_skill_date_time-1.1.5.dist-info/METADATA
ovos_skill_date_time-1.1.5.dist-info/WHEEL
ovos_skill_date_time-1.1.5.dist-info/entry_points.txt
ovos_skill_date_time-1.1.5.dist-info/top_level.txt
ovos_skill_date_time-1.1.5.dist-info/RECORD
