Metadata-Version: 2.1
Name: ovos-skill-date-time
Version: 1.1.5
Summary: ovos skill plugin
Home-page: https://github.com/OpenVoiceOS/ovos-skill-date-time
Author: OpenVoiceOS
License: Apache-2.0
Keywords: ovos skill plugin
License-File: LICENSE
Requires-Dist: pytz>=2025.2
Requires-Dist: tzlocal>=5.3.1
Requires-Dist: timezonefinder>=6.5.9
Requires-Dist: geocoder~=1.38
Requires-Dist: ovos-utils>=0.8.1
Requires-Dist: ovos-workshop<8.0.0,>=0.0.16
Requires-Dist: ovos-date-parser<1.0.0,>=0.0.1
Requires-Dist: ovos-utterance-normalizer<1.0.0,>=0.0.1
